Metadata-Version: 1.1
Name: yara
Version: 1.7.6
Summary: Compile YARA rules to test against files or strings
Home-page: http://code.google.com/p/yara-project/
Author: Michael Dorman
Author-email: mjdorma@gmail.com
License: Apache Software Licence
Platform: cygwin
Platform: win
Platform: linux
Classifier: Development Status :: 2 - Pre-Alpha
Classifier: Intended Audience :: Other Audience
Classifier: License :: OSI Approved :: Apache Software License
Classifier: Operating System :: Microsoft :: Windows
Classifier: Operating System :: POSIX :: Linux
Classifier: Programming Language :: Python
Classifier: Programming Language :: Python :: 2.6
Classifier: Programming Language :: Python :: 2.7
Classifier: Programming Language :: Python :: 3
Classifier: Programming Language :: Python :: 3.2
Classifier: Programming Language :: Python :: 3.3
Classifier: Programming Language :: Python :: Implementation :: CPython
Classifier: Topic :: Security
Classifier: Topic :: System :: Monitoring
